CHANGES.txt
DISCLAIMER.txt
LICENSE.txt
MANIFEST.in
setup.py
cloudstack_marvin.egg-info/PKG-INFO
cloudstack_marvin.egg-info/SOURCES.txt
cloudstack_marvin.egg-info/dependency_links.txt
cloudstack_marvin.egg-info/entry_points.txt
cloudstack_marvin.egg-info/not-zip-safe
cloudstack_marvin.egg-info/requires.txt
cloudstack_marvin.egg-info/top_level.txt
marvin/__init__.py
marvin/asyncJobMgr.py
marvin/cloudstackConnection.py
marvin/cloudstackException.py
marvin/cloudstackTestCase.py
marvin/cloudstackTestClient.py
marvin/codegenerator.py
marvin/codes.py
marvin/configGenerator.py
marvin/dbConnection.py
marvin/deployAndRun.py
marvin/deployDataCenter.py
marvin/jsonHelper.py
marvin/marvinInit.py
marvin/marvinLog.py
marvin/marvinPlugin.py
marvin/settings.py
marvin/sshClient.py
marvin/tcExecuteEngine.py
marvin/testSetupSuccess.py
marvin/cloudstackAPI/__init__.py
marvin/cloudstackAPI/activateProject.py
marvin/cloudstackAPI/addAccountToProject.py
marvin/cloudstackAPI/addBaremetalDhcp.py
marvin/cloudstackAPI/addBaremetalHost.py
marvin/cloudstackAPI/addBaremetalPxeKickStartServer.py
marvin/cloudstackAPI/addBaremetalPxePingServer.py
marvin/cloudstackAPI/addBigSwitchVnsDevice.py
marvin/cloudstackAPI/addCluster.py
marvin/cloudstackAPI/addGuestOs.py
marvin/cloudstackAPI/addGuestOsMapping.py
marvin/cloudstackAPI/addHost.py
marvin/cloudstackAPI/addImageStore.py
marvin/cloudstackAPI/addIpToNic.py
marvin/cloudstackAPI/addLdapConfiguration.py
marvin/cloudstackAPI/addNetscalerLoadBalancer.py
marvin/cloudstackAPI/addNetworkDevice.py
marvin/cloudstackAPI/addNetworkServiceProvider.py
marvin/cloudstackAPI/addNicToVirtualMachine.py
marvin/cloudstackAPI/addNiciraNvpDevice.py
marvin/cloudstackAPI/addPaloAltoFirewall.py
marvin/cloudstackAPI/addRegion.py
marvin/cloudstackAPI/addResourceDetail.py
marvin/cloudstackAPI/addS3.py
marvin/cloudstackAPI/addSecondaryStorage.py
marvin/cloudstackAPI/addStratosphereSsp.py
marvin/cloudstackAPI/addSwift.py
marvin/cloudstackAPI/addTrafficMonitor.py
marvin/cloudstackAPI/addTrafficType.py
marvin/cloudstackAPI/addUcsManager.py
marvin/cloudstackAPI/addVpnUser.py
marvin/cloudstackAPI/archiveAlerts.py
marvin/cloudstackAPI/archiveEvents.py
marvin/cloudstackAPI/assignCertToLoadBalancer.py
marvin/cloudstackAPI/assignToGlobalLoadBalancerRule.py
