Metadata-Version: 1.0
Name: cloudstack-marvin
Version: 4.4.0
Summary: Marvin - Python client for Apache CloudStack
Home-page: https://builds.apache.org/job/cloudstack-marvin/
Author: Prasanna Santhanam
Author-email: tsp@apache.org
License: LICENSE.txt
Platform: Any
